MANIFEST.in
README.md
linter.py
requirements.txt
setup.cfg
setup.py
linter_cli.egg-info/PKG-INFO
linter_cli.egg-info/SOURCES.txt
linter_cli.egg-info/dependency_links.txt
linter_cli.egg-info/entry_points.txt
linter_cli.egg-info/requires.txt
linter_cli.egg-info/top_level.txt