Metadata-Version: 1.1
Name: linter-cli
Version: 0.0.2
Summary: CLI client for lint service
Home-page: https://github.com/eodolphi/linter-cli
Author: Ernst Odolphi
Author-email: ernst.odolphi@onepercentclub.com
License: BSD
Download-URL: https://github.com/eodolphi/linter-cli/tarball/0.0.2
Platform: UNKNOWN
Classifier: Development Status :: 3 - Alpha
Classifier: Intended Audience :: Developers
Classifier: Programming Language :: Python :: 3
